enka/__init__.py
enka/assets/data.py
enka/assets/gi/file_paths.py
enka/assets/gi/manager.py
enka/assets/hsr/file_paths.py
enka/assets/hsr/manager.py
enka/assets/manager.py
enka/assets/zzz/file_paths.py
enka/assets/zzz/manager.py
enka/calc/hsr.py
enka/calc/zzz.py
enka/clients/__init__.py
enka/clients/base.py
enka/clients/cache.py
enka/clients/gi.py
enka/clients/hsr.py
enka/clients/zzz.py
enka/constants/common.py
enka/constants/gi.py
enka/constants/hsr.py
enka/constants/zzz.py
enka/enums/__init__.py
enka/enums/enum.py
enka/enums/gi.py
enka/enums/hsr.py
enka/enums/zzz.py
enka/errors.py
enka/gi.py
enka/hsr.py
enka/models/__init__.py
enka/models/enka/__init__.py
enka/models/enka/build.py
enka/models/enka/owner.py
enka/models/gi/__init__.py
enka/models/gi/build.py
enka/models/gi/character.py
enka/models/gi/costume.py
enka/models/gi/icon.py
enka/models/gi/player.py
enka/models/gi/response.py
enka/models/hsr/__init__.py
enka/models/hsr/build.py
enka/models/hsr/character.py
enka/models/hsr/icon.py
enka/models/hsr/player.py
enka/models/hsr/response.py
enka/models/zzz/__init__.py
enka/models/zzz/build.py
enka/models/zzz/character.py
enka/models/zzz/icon.py
enka/models/zzz/player.py
enka/models/zzz/response.py
enka/utils.py
enka/zzz.py
enka-2.5.16.dist-info/WHEEL
enka-2.5.16.dist-info/METADATA
enka-2.5.16.dist-info/RECORD
