Metadata-Version: 2.3
Name: enka
Version: 2.5.16
Summary: Async API wrapper for Enka Network written in Python, supports GI, HSR, and ZZZ.
Author: seriaati
Author-email: seriaati <seria.ati@gmail.com>
License: GNU GENERAL PUBLIC LICENSE
Requires-Dist: aiofiles>=24.1.0
Requires-Dist: aiohttp>=3.10.9
Requires-Dist: deprecated>=1.2.18
Requires-Dist: loguru>=0.7.2
Requires-Dist: orjson>=3.10.7
Requires-Dist: pydantic>=2.9.2
Requires-Dist: redis[hiredis]>=6.2.0 ; extra == 'redis'
Requires-Dist: aiosqlite>=0.20.0 ; extra == 'sqlite'
Requires-Python: >=3.10
Project-URL: Documentation, https://gh.seria.moe/enka-py
Project-URL: Homepage, https://github.com/seriaati/enka-py
Project-URL: Issues, https://github.com/seriaati/enka-py/issues
Project-URL: Repository, https://github.com/seriaati/enka-py.git
Provides-Extra: redis
Provides-Extra: sqlite
